date_master/__init__.py
date_master/backup.py
date_master/changeformat.py
date_master/changeorder.py
date_master/date.py
date_master/exceptions.py
date_master/numbertoword.py
date_master/validation.py
date_master-2.0.2.dist-info/LICENSE
date_master-2.0.2.dist-info/METADATA
date_master-2.0.2.dist-info/WHEEL
date_master-2.0.2.dist-info/top_level.txt
date_master-2.0.2.dist-info/RECORD
