Metadata-Version: 2.1
Name: date_master
Version: 2.0.2
Summary: Date Master - A complete date solution
Home-page: https://github.com/programspeaker/date_master
Author: Sarath Chandran
Author-email: programspeaker@gmail.com
Maintainer: Sarath Chandran
Maintainer-email: sarath1plaza@gmail.com
License: MIT
Keywords: date_master
Classifier: Development Status :: 5 - Production/Stable
Classifier: Intended Audience :: Developers
Classifier: License :: OSI Approved :: MIT License
Classifier: Operating System :: OS Independent
Classifier: Programming Language :: Python
Classifier: Programming Language :: Python :: 3
Classifier: Programming Language :: Python :: 3 :: Only
Classifier: Programming Language :: Python :: 3.6
Classifier: Programming Language :: Python :: 3.7
Classifier: Programming Language :: Python :: 3.8
Classifier: Topic :: Software Development :: Libraries :: Python Modules
License-File: LICENSE
